ollama_call/__init__.py
ollama_call-1.0.0.dist-info/licenses/LICENSE
ollama_call-1.0.0.dist-info/METADATA
ollama_call-1.0.0.dist-info/WHEEL
ollama_call-1.0.0.dist-info/top_level.txt
ollama_call-1.0.0.dist-info/RECORD
