Metadata-Version: 2.4
Name: ollama-call
Version: 1.0.0
Summary: A simple Python wrapper for Ollama API
Author-email: Demensdeum <your-email@example.com>
Project-URL: Homepage, https://github.com/demensdeum/ollama_call
Project-URL: Bug Tracker, https://github.com/demensdeum/ollama_call/issues
Classifier: Programming Language :: Python :: 3
Classifier: License :: OSI Approved :: MIT License
Classifier: Operating System :: OS Independent
Requires-Python: >=3.7
License-File: LICENSE
Requires-Dist: requests
Dynamic: license-file
